s2a/__init__.py
s2a/cli.py
s2a/main.py
stereoseq_to_adata-0.3.1.dist-info/METADATA
stereoseq_to_adata-0.3.1.dist-info/WHEEL
stereoseq_to_adata-0.3.1.dist-info/entry_points.txt
stereoseq_to_adata-0.3.1.dist-info/licenses/LICENSE
stereoseq_to_adata-0.3.1.dist-info/RECORD
