Metadata-Version: 2.4
Name: stereoseq-to-adata
Version: 0.3.1
Summary: Quickly convert parquet files exported from stereo-seq to adata format and add appropriate metadata
Project-URL: GitHub, https://github.com/myuanz/stereoseq-to-adata
Author: myuan
License: MIT
License-File: LICENSE
Requires-Python: >=3.11
Requires-Dist: anndata>=0.11.3
Requires-Dist: polars>=1.22.0
Requires-Dist: scanpy>=1.10.4
Requires-Dist: tyro>=1.0.2
